privattacks/__init__.py
privattacks/attacks.py
privattacks/data.py
privattacks/util.py
privattacks-1.4.dist-info/licenses/LICENSE
privattacks-1.4.dist-info/METADATA
privattacks-1.4.dist-info/WHEEL
privattacks-1.4.dist-info/top_level.txt
privattacks-1.4.dist-info/RECORD
