Metadata-Version: 2.4
Name: privattacks
Version: 1.4
Summary: Privattacks is a Python package for evaluating privacy risks in tabular datasets. It provides tools to quantify re-identification and attribute inference vulnerabilities based on combinations of quasi-identifiers an adversary knows about a target. The package supports both high-level and granular analysis, including per-record vulnerability distributions, multiprocessing for efficiency, and flexible input handling via pandas DataFrames and other sources.
Home-page: https://github.com/ramongonze/privattacks
Author: Ramon Gonçalves Gonze
Author-email: Ramon Gonçalves Gonze <ramongonze@gmail.com>
License-Expression: MIT
Project-URL: Documentation, https://privattacks.readthedocs.io/
Project-URL: Repository, https://github.com/ramongonze/privattacks.git
Project-URL: Issues, https://github.com/ramongonze/privattacks/issues
Classifier: Programming Language :: Python :: 3
Classifier: Operating System :: OS Independent
Requires-Python: >=3.9
License-File: LICENSE
Requires-Dist: pandas>=2.2.3
Requires-Dist: numpy>=2.0.2
Requires-Dist: tqdm>=4.65.0
Requires-Dist: pyreadr>=0.5.2
Dynamic: author
Dynamic: home-page
Dynamic: license-file
Dynamic: requires-python
